Metadata-Version: 1.0
Name: mol-distributions
Version: 0.1
Summary: Gaussian distributions
Home-page: UNKNOWN
Author: Alex Poulain
Author-email: UNKNOWN
License: UNKNOWN
Platform: UNKNOWN
